polySim/__init__.py
polySim/libpolySim.cp37-win_amd64.pyd
polySim/wrapper.py
polySim/c_code/main.cpp
polySim/c_code/main.h
polySim-0.1.1.dist-info/LICENSE.txt
polySim-0.1.1.dist-info/METADATA
polySim-0.1.1.dist-info/WHEEL
polySim-0.1.1.dist-info/top_level.txt
polySim-0.1.1.dist-info/RECORD
