Metadata-Version: 2.1
Name: polySim
Version: 0.1.1
Summary: Polycrystalline microstructure simulation package
Home-page: https://github.com/nikolspace/polySim
Author: Nikhil Chaurasia Sandeep Sangal, Shikhar Krishn Jha
Author-email: nikolspace@gmail.com
License: MIT
Classifier: Programming Language :: Python :: 3.7
Classifier: Programming Language :: Python :: 3.8
Classifier: Programming Language :: Python :: 3.9
Classifier: Programming Language :: Python :: 3.10
Classifier: Programming Language :: Python :: 3.11
Classifier: Programming Language :: Python :: 3.12
Classifier: Programming Language :: C++
Classifier: Operating System :: OS Independent
Classifier: License :: OSI Approved :: MIT License
Classifier: Development Status :: 4 - Beta
Classifier: Intended Audience :: Science/Research
Classifier: Topic :: Scientific/Engineering
Requires-Python: >=3.6
License-File: LICENSE.txt
Requires-Dist: numpy
